tmasque/Chromatogram.py
tmasque/PeakQualityControl.py
tmasque/QualityEncoder.py
tmasque/TargetedMSQC.py
tmasque/TargetedMSQualityEncoder.py
tmasque/__init__.py
tmasque/tmasque_runner.py
tmasque/encoder/quality_encoder_type1.pickle
tmasque/encoder/quality_encoder_type2.pickle
tmasque/encoder/quality_encoder_type3.pickle
tmasque/example/CPTC-EGFR-5_YSSD_2.tsv
tmasque/example/PeakBoundaries.csv
tmasque-0.8.5.dist-info/LICENSE
tmasque-0.8.5.dist-info/METADATA
tmasque-0.8.5.dist-info/WHEEL
tmasque-0.8.5.dist-info/entry_points.txt
tmasque-0.8.5.dist-info/top_level.txt
tmasque-0.8.5.dist-info/RECORD
