Metadata-Version: 2.1
Name: tmasque
Version: 0.8.5
Summary: This targeted mass spectrometry quality encoder (tmasque) evaluates peak quality systematically for targeted mass spectrometry.
Author-email: Chi Yang <chiyang@mail.cgu.edu.tw>
License: MIT License
Project-URL: Homepage, https://github.com/ChiYang/tmasque
Project-URL: Repository, https://github.com/ChiYang/tmasque
Project-URL: Bug Tracker, https://github.com/ChiYang/tmasque/issues
Requires-Python: >=3.8
License-File: LICENSE
Requires-Dist: numpy
Requires-Dist: pandas
Requires-Dist: xlsxwriter
Requires-Dist: matplotlib >=3.6.3
Requires-Dist: torch >=1.11
